sidd/__init__.py
sidd/siddcolors.py
sidd/siddcompares.py
sidd/siddmain.py
sidd-1.dist-info/LICENSE
sidd-1.dist-info/METADATA
sidd-1.dist-info/WHEEL
sidd-1.dist-info/top_level.txt
sidd-1.dist-info/RECORD
